{
  "project_info": {
    "project_number": "972733993724",
    "project_id": "todoapp-b0aee",
    "storage_bucket": "todoapp-b0aee.appspot.com"
  },
  "client": [
    {
      "client_info": {
        "mobilesdk_app_id": "1:972733993724:android:38be004307d21fca5dfd79",
        "android_client_info": {
          "package_name": "com.example.todoapp"
        }
      },
      "oauth_client": [],
      "api_key": [
        {
          "current_key": "AIzaSyDCYGe9d9ZHIZ5vE3OjAHWYCfSKJhreT98"
        }
      ],
      "services": {
        "appinvite_service": {
          "other_platform_oauth_client": []
        }
      }
    }
  ],
  "configuration_version": "1"
}